odoo10_addon_report_qweb_txt-10.0.1.0.0.99.dev8-py2.7-nspkg.pth
odoo/addons/report_qweb_txt/README.rst
odoo/addons/report_qweb_txt/__init__.py
odoo/addons/report_qweb_txt/__manifest__.py
odoo/addons/report_qweb_txt/demo/report.xml
odoo/addons/report_qweb_txt/demo/res_users_report.xml
odoo/addons/report_qweb_txt/i18n/ca.po
odoo/addons/report_qweb_txt/i18n/da.po
odoo/addons/report_qweb_txt/i18n/de.po
odoo/addons/report_qweb_txt/i18n/el_GR.po
odoo/addons/report_qweb_txt/i18n/es.po
odoo/addons/report_qweb_txt/i18n/es_CO.po
odoo/addons/report_qweb_txt/i18n/fr.po
odoo/addons/report_qweb_txt/i18n/gl.po
odoo/addons/report_qweb_txt/i18n/hr.po
odoo/addons/report_qweb_txt/i18n/hr_HR.po
odoo/addons/report_qweb_txt/i18n/it.po
odoo/addons/report_qweb_txt/i18n/nb_NO.po
odoo/addons/report_qweb_txt/i18n/nl_NL.po
odoo/addons/report_qweb_txt/i18n/pl.po
odoo/addons/report_qweb_txt/i18n/pt.po
odoo/addons/report_qweb_txt/i18n/pt_BR.po
odoo/addons/report_qweb_txt/i18n/pt_PT.po
odoo/addons/report_qweb_txt/i18n/report_qweb_txt.pot
odoo/addons/report_qweb_txt/i18n/sl.po
odoo/addons/report_qweb_txt/i18n/tr.po
odoo/addons/report_qweb_txt/i18n/tr_TR.po
odoo/addons/report_qweb_txt/models/__init__.py
odoo/addons/report_qweb_txt/models/ir_actions_report_xml.py
odoo/addons/report_qweb_txt/models/report.py
odoo/addons/report_qweb_txt/static/description/icon.png
odoo10_addon_report_qweb_txt-10.0.1.0.0.99.dev8.dist-info/METADATA
odoo10_addon_report_qweb_txt-10.0.1.0.0.99.dev8.dist-info/RECORD
odoo10_addon_report_qweb_txt-10.0.1.0.0.99.dev8.dist-info/WHEEL
odoo10_addon_report_qweb_txt-10.0.1.0.0.99.dev8.dist-info/namespace_packages.txt
odoo10_addon_report_qweb_txt-10.0.1.0.0.99.dev8.dist-info/top_level.txt
